potoken_generator/__init__.py
potoken_generator/extractor.py
potoken_generator/main.py
potoken_generator/server.py
youtube_trusted_session_generator-0.0.4.dist-info/licenses/LICENSE
youtube_trusted_session_generator-0.0.4.dist-info/METADATA
youtube_trusted_session_generator-0.0.4.dist-info/WHEEL
youtube_trusted_session_generator-0.0.4.dist-info/entry_points.txt
youtube_trusted_session_generator-0.0.4.dist-info/top_level.txt
youtube_trusted_session_generator-0.0.4.dist-info/RECORD
