Metadata-Version: 2.4
Name: youtube-trusted-session-generator
Version: 0.0.4
Summary: syncs youtube for offline play
Maintainer: Zachary Vorhies
License-Expression: BSD-3-Clause
Keywords: template-python-cmd
Classifier: Programming Language :: Python :: 3
Requires-Python: >=3.10
License-File: LICENSE
Requires-Dist: nodriver==0.32
Requires-Dist: undetected-chromedriver==3.5.5
Requires-Dist: websockets==13.1
Dynamic: license-file
